LoveZC/__init__.py
LoveZC/love_zc.py
LoveZC-0.0.1.dist-info/LICENSE.txt
LoveZC-0.0.1.dist-info/METADATA
LoveZC-0.0.1.dist-info/WHEEL
LoveZC-0.0.1.dist-info/entry_points.txt
LoveZC-0.0.1.dist-info/top_level.txt
LoveZC-0.0.1.dist-info/RECORD
